[
  {
    "content_id": 146068,
    "reference_id": 108559,
    "title": "Água viva",
    "media_type": "Text",
    "index_reference": "água viva",
    "language": "por",
    "content": "<p>Uma maneira de falar sobre como Deus provê tudo o que as pessoas precisam para viver. Na Bíblia, também é chamada de água que dá vida e água da vida. A água é viva quando é fresca e corrente. As pessoas a bebem para se manterem vivas, e plantas e animais podem viver nela. Os profetas descreveram Deus como uma fonte de água que dava vida ao seu povo. Eles o descreveram como um pastor que conduzia seu povo a fontes de água. E descreveram como a água fluiria de Jerusalém. Essa água daria vida ao mundo inteiro. No Novo Testamento, Jesus descreveu o Espírito Santo como água viva. Jesus dá água viva às pessoas que acreditam nele. Isso significa que ele compartilha o Espírito Santo com elas. O Espírito provê o que seus espíritos precisam. Isso é como a água que provê o que seus corpos precisam. O Espírito os ajuda a servir aos outros. É assim que a água viva flui de dentro das pessoas. Em Apocalipse, Deus oferece a água da vida gratuitamente a todos que acreditam nele.</p>",
    "associations": {
      "passage": [],
      "resource": []
    }
  }
]