[
  {
    "content_id": 145868,
    "reference_id": 108359,
    "title": "Água especial",
    "media_type": "Text",
    "index_reference": "água especial",
    "language": "por",
    "content": "<p>A água era usada em muitas práticas para ajudar os israelitas a adorar a Deus. Os sacerdotes lavavam as mãos e os pés com água quando serviam a Deus no altar. Essa água era mantida em uma grande bacia de bronze. Pessoas e coisas que eram consideradas impuras tornavam-se limpas após serem lavadas com água. A água era considerada especial quando os sacerdotes adicionavam cinzas de uma vaca jovem a ela. Essa água especial era aspergida em pessoas ou coisas que estiveram próximas de um corpo morto. Usar água dessas maneiras significava mais do que limpar a sujeira. Era um sinal de que pessoas ou coisas eram consideradas espiritualmente limpas e puras. Somente pessoas ou coisas que eram consideradas limpas e puras podiam estar próximas a Deus.</p>",
    "associations": {
      "passage": [],
      "resource": []
    }
  }
]