[
  {
    "content_id": 146057,
    "reference_id": 108548,
    "version": "1.0.0",
    "title": "Espada",
    "media_type": "Text",
    "index_reference": "espada",
    "language": "por",
    "content": "<p>Uma arma afiada usada para lutar. Escritores na Bíblia disseram que as palavras que as pessoas falam são como espadas. Isso mostrou como as pessoas podem causar dano com suas palavras. Escritores na Bíblia também disseram que a palavra de Deus é como uma espada. Isso mostrou que a palavra de Deus revela o que está dentro dos corações das pessoas. Também mostrou que a palavra de Deus fortalece e protege os crentes quando eles lutam contra o mal. De uma maneira especial, as palavras da boca de Jesus foram descritas como uma espada. Isso foi uma imagem de como Jesus é a palavra de Deus. Tudo o que ele fala é a verdade sobre Deus. Falar a verdade sobre Deus é como ele destrói as mentiras do diabo sobre Deus.</p>",
    "associations": {
      "passage": [],
      "resource": []
    }
  }
]