[
  {
    "content_id": 146029,
    "reference_id": 108520,
    "version": "1.0.0",
    "title": "Mardoqueu (Mordecai)",
    "media_type": "Text",
    "index_reference": "mardoqueu (mordecai)",
    "language": "por",
    "content": "<p>Um judeu que viveu no reino persa durante o tempo de Xerxes. Mardoqueu (ou Mordecai, como em algumas Bíblias) era filho de Jair e era da tribo de Benjamim. Ele adotou sua prima Ester quando os pais dela morreram. Ele serviu no governo persa no portão do palácio em Susa. Depois que Hamã foi morto, Mardoqueu se tornou um conselheiro de Xerxes. Mardoqueu era um líder importante com autoridade no reino persa.</p>",
    "associations": {
      "passage": [],
      "resource": []
    }
  }
]