[
  {
    "content_id": 145828,
    "reference_id": 108319,
    "version": "1.0.0",
    "title": "Salvador",
    "media_type": "Text",
    "index_reference": "salvador",
    "language": "por",
    "content": "<p>Deus salvou os israelitas da escravidão no Egito. Ele os salvou de seus inimigos muitas vezes ao longo do Antigo Testamento. Ele era o único poderoso o suficiente para salvá-los. Dessa forma, ele se mostrou ser o único Salvador deles. Ele também prometeu enviar um Salvador que viveria entre eles. Este era Jesus, o Messias. Jesus salva aqueles que acreditam nele e o seguem. Ele os salva do poder do pecado, da morte e do mal.</p>",
    "associations": {
      "passage": [],
      "resource": []
    }
  }
]