[
  {
    "content_id": 133933,
    "reference_id": 108131,
    "title": "الرُواقيُّون",
    "media_type": "Text",
    "index_reference": "الرُواقيُّون",
    "language": "arb",
    "content": "<p>مجموعة من الفلاسفة الذين اتبعوا تعاليم الفيلسوف اليوناني زينو من كتّيم. كانوا يعتقدون أن الناس يجب أن يعيشوا وفقًا لقوانين طبيعية تسمى اللوغوس. كان اللوغوس يُفهم على أنه قوة العقل التي تجعل العالم يعمل. شارك بولس الأخبار السارة عن يسوع مع الرواقيين في أثينا.</p>",
    "associations": {
      "passage": [],
      "resource": []
    }
  }
]