[
  {
    "content_id": 134284,
    "reference_id": 108482,
    "version": "1.0.0",
    "title": "آسا",
    "media_type": "Text",
    "index_reference": "آسا",
    "language": "arb",
    "content": "<p>ابن  أبيام وأب يهوشافاط. كان من سبط يهوذا. كان الملك الثالث لمملكة يهوذا الجنوبية. لسنوات عديدة اتبع الله بأمانة. كان ثالث ملوك مملكة يهوذا الجنوبية. لسنوات عديدة اتبع الله بأمانة. قاد الشعب إلى عبادة الله وحده. فيما بعد توقف عن الثقة بالله وبدأ يسيئ معاملة شعب الله.</p>",
    "associations": {
      "passage": [],
      "resource": []
    }
  }
]