[
  {
    "content_id": 134140,
    "reference_id": 108338,
    "title": "ذبائح حيوانية",
    "media_type": "Text",
    "index_reference": "ذبائح حيوانية",
    "language": "arb",
    "content": "<p>هي طريقة معينة لتقديم وذبح الحيوانات. وكان يتم القيام بذلك من أجل عبادة وتكريم شخص ما أو إله. ولقد كانت هذه الممارسة شائعة ومعروفة في الأزمنة والأماكن المُسجّلة في الكتاب المقدس. كان الذين يعبدون الإله الحقيقي يقدّمون ذبائح من الحيوانات لإظهار توبتهم عن الخطية. فكان موت الحيوان إشارة على الموت والأذى الذي تجلبه الخطية. وقد كان أيضًا علامة على عقاب الخطايا التي يرتكبها البشر. فقد كانت الحيوانات تُذبح وتموت بدلاً عن البشر. وبهذه الطريقة كانت الحيوانات تُقدّم للتكفير عن خطايا الناس. أما الناس الذين يعبدون الآلهة المزيفة فكانوا يقدمون الذبائح الحيوانية لأسباب مختلفة. فكانوا يفعلون ذلك لإظهار مدى التزامهم تجاه عبادة آلهتهم المزيفة . كما كانوا يفعلون ذلك للحصول على بركة. وأيضًا، فقد كانوا يقدّمون هذه الذبائح لأنهم كانوا يعتقدون أن الآلهة المزيفة جائعة أو غاضبة.</p>",
    "associations": {
      "passage": [],
      "resource": []
    }
  }
]