[
  {
    "content_id": 134151,
    "reference_id": 108349,
    "version": "1.0.0",
    "title": "ثياب الكهنة",
    "media_type": "Text",
    "index_reference": "ثياب الكهنة",
    "language": "arb",
    "content": "<p>ملابس خاصة كان الكهنة يرتدونها عندما يعملون في خيمة الإجتماع أو الهيكل. تضمنت الملابس رِداءً خارجيًا ورِداءً داخليًا وسروال ومِنْطَقَةٌ. وكانت تتضمن عِمَامَةٌ عليها صَفِيحَةً مِنْ ذَهَبٍ. كانت ملابس رئيس الكهنة تتضمن قَمِيصٌ مُخَرَّمٌ كتان وقطعة قماش على الصدر. كان قماش الصدر يحمل الأوريم والتميم. كانت هذه أحجار كريمة تساعد الكاهن على معرفة إرادة الله في الأمور. ساعدت ملابس الكهنة على تمييز الكهنة عن غيرهم في عملهم من أجل الله.</p>",
    "associations": {
      "passage": [],
      "resource": []
    }
  }
]