[
  {
    "content_id": 133701,
    "reference_id": 108449,
    "title": "David",
    "media_type": "Text",
    "index_reference": "david",
    "language": "fra",
    "content": "<p>Fils de Jessé de la tribu de Juda. Il était issu de la lignée de Ruth. David était berger dans sa jeunesse. Il a suivi Dieu fidèlement et est devenu le roi le plus célèbre d&apos;Israël. Il jouait d&apos;un instrument de musique et écrivait des chansons et des poèmes. Il était fidèle à Dieu et n&apos;adorait que lui. Tous les rois qui l&apos;ont suivi lui ont été comparés. Dieu a conclu une alliance avec lui. (<span data-bnType=\"resourceReference\" data-resourceId=\"108466\" data-resourceType=\"BiblicaStudyNotesKeyTerms\">L&apos;alliance avec David</span>)</p><p></p><p></p>",
    "associations": {
      "passage": [],
      "resource": [
        {
          "reference_id": 108466,
          "content_id": 133718,
          "resource_code": "BiblicaStudyNotesKeyTerms",
          "label": "Alliance avec David",
          "language": "fra"
        }
      ]
    }
  }
]