[
  {
    "content_id": 133528,
    "reference_id": 108276,
    "version": "1.0.0",
    "title": "Rachel",
    "media_type": "Text",
    "index_reference": "rachel",
    "language": "fra",
    "content": "<p>Rachel était la deuxième fille de Laban et la deuxième femme de Jacob. Léa était sa sœur et Bila sa servante. Rachel était bergère. Jacob l&apos;aimait plus qu&apos;il n&apos;aimait Léa. Elle a donné naissance à Joseph et Benjamin.</p>",
    "associations": {
      "passage": [],
      "resource": []
    }
  }
]