[
  {
    "content_id": 133464,
    "reference_id": 108212,
    "title": "Repos",
    "media_type": "Text",
    "index_reference": "repos",
    "language": "fra",
    "content": "<p>Dans la Bible, le mot repos a plusieurs significations. La première signification est mentionnée dans le chapitre 2 de la Genèse. Après avoir terminé son travail de création du monde, Dieu s&apos;est reposé. La paix régnait entre lui et ce qu&apos;il avait créé. L&apos;univers entier avait tout le nécessaire pour vivre en conformité avec la volonté de Dieu. Une autre signification est mentionnée dans les Dix Commandements. C&apos;est le repos du Sabbat. Le septième jour de la semaine, les Israélites devaient se reposer au lieu de travailler. Une troisième signification se trouve dans le Psaume 95, où il est question du repos que les Israélites ont connus après avoir été libérés de l&apos;esclavage. Dieu les a conduits dans le pays qu&apos;il leur avait promis de leur donner. Enfin, les chapitres 3 et 4 de l&apos;épître aux Hébreux décrivent la pleine signification du repos selon la Bible. Jésus apporte le vrai repos à ceux qui croient en lui. Ils commencent à jouir du repos de Jésus lorsqu&apos;ils se mettent à le suivre. Ils en profiteront pleinement lorsqu&apos;il régnera complètement en tant que roi.</p>",
    "associations": {
      "passage": [],
      "resource": []
    }
  }
]