[
  {
    "content_id": 133380,
    "reference_id": 108128,
    "version": "1.0.0",
    "title": "Thessalonique",
    "media_type": "Text",
    "index_reference": "thessalonique",
    "language": "fra",
    "content": "<p>Une ville grecque du territoire romain de Macédoine. C&apos;était dans la région qui est désormais le nord de la Grèce. Paul s&apos;y est rendu lors de son deuxième voyage. Ses lettres aux Thessaloniciens ont été écrites pour l&apos;église de cette région.</p>",
    "associations": {
      "passage": [],
      "resource": []
    }
  }
]