[
  {
    "content_id": 193275,
    "reference_id": 108193,
    "version": "1.0.0",
    "title": "Библия",
    "media_type": "Text",
    "index_reference": "библия",
    "language": "rus",
    "content": "<p>Книга священных писаний иудеев и христиан. В состав еврейской Библии входят только книги Ветхого Завета. Библия христиан состоит из книг Ветхого и Нового Заветов (<span data-bnType=\"resourceReference\" data-resourceId=\"108200\" data-resourceType=\"BiblicaStudyNotesKeyTerms\">Божье Слово</span>).</p>",
    "associations": {
      "passage": [],
      "resource": [
        {
          "reference_id": 108200,
          "content_id": 193282,
          "resource_code": "BiblicaStudyNotesKeyTerms",
          "label": "Божье слово",
          "language": "rus"
        }
      ]
    }
  }
]