[
  {
    "content_id": 193250,
    "reference_id": 108168,
    "title": "Иуда, брат Иисуса",
    "media_type": "Text",
    "index_reference": "иуда, брат иисуса",
    "language": "rus",
    "content": "<p>Один из братьев Иисуса Христа. Сначала он не верил, что Иисус — Христос. Однако потом он уверовал в Иисуса и стал известным руководителем среди христианских церквей. Считается, что <span>Иуда является автором Послания </span>Иуды. </p>",
    "associations": {
      "passage": [],
      "resource": []
    }
  }
]