[
  {
    "content_id": 193114,
    "reference_id": 108032,
    "version": "1.0.0",
    "title": "Иосиф из Назарета",
    "media_type": "Text",
    "index_reference": "иосиф из назарета",
    "language": "rus",
    "content": "<p>Иосиф из Назарета был мужем Марии, Матери Иисуса. Он происходил из рода Давида и от всего сердца служил Богу. Иосиф был искусным мастером в работе с деревом, металлом и кирпичом. Он не был биологическим отцом Иисуса, но воспитывал его как своего. Иосиф заботился об Иисусе и защищал Его, когда Тот был Ребёнком.</p>",
    "associations": {
      "passage": [],
      "resource": []
    }
  }
]