[
  {
    "content_id": 193470,
    "reference_id": 108388,
    "title": "Святой Дух",
    "media_type": "Text",
    "index_reference": "святой дух",
    "language": "rus",
    "content": "<p><span>При сотворения мира Бог действовал как Дух. Святой Дух является Богом так же как Небесный Отец и Иисус. Отец, Сын и Святой Дух — это три личности единого Бога. Святой Дух действовал через людей, которые писали священные тексты (Библию). В Ветхом Завете Святой Дух давал людям способность пророчествовать. Он также помогал людям выполнять искусную работу и совершать великие подвиги. В Новом Завете Святой Дух дал Марии способность стать матерью Иисуса. Иисус дал Святого Духа Своим ученикам в праздник Пятидесятницы. Б</span>лагодаря Святому Духу верующие соединяются с Иисусом<span>. Святой Дух </span>—<span> это наш Друг, Который помогает всем верующим продолжать на земле дело Божьего Сына. </span></p>",
    "associations": {
      "passage": [],
      "resource": []
    }
  }
]