[
  {
    "content_id": 183394,
    "reference_id": 108500,
    "version": "1.0.0",
    "title": "परमेश्वर का क्रोध",
    "media_type": "Text",
    "index_reference": "परमेश्वर का क्रोध",
    "language": "hin",
    "content": "<p>बाइबिल परमेश्वर को पाप और बुराई पर क्रोध करने वाले के रूप में वर्णित करती है। जो बुराई करना बंद नहीं करते हैं, वह उन लोगों के खिलाफ न्याय लाकर अपना गुस्सा दिखाते हैं। वह उन लोगों के खिलाफ न्याय लाता है जो इनकार करते हैं पश्चाताप करने से और पाप से दूर होने से। बाइबिल के लेखकों ने परमेश्वर के क्रोध को दाखरस के कुण्ड के समान बताया। एक दाखरस के कुण्ड में, दाखरस बनाने के लिए अंगूर को कुचल दिया जाता है। बाइबिल के लेखकों ने भी परमेश्वर के क्रोध को दाखमधु के प्याले के समान वर्णित किया है। जिन लोगों ने पाप करना और बुरे काम करना बंद करने से इनकार कर दिया, उन्हें इसे पीना पड़ा। ये परमेश्वर के न्याय की तस्वीरें थीं। वे चित्र थे कि कैसे परमेश्वर बुराई करने वालों को रोकता है और उन्हें दण्ड देता है। जो लोग यीशु पर विश्वास करते हैं वे पाप और बुराई की शक्ति से मुक्त हो जाते हैं। इस वजह से, वे पाप और बुराई के खिलाफ परमेश्वर के क्रोध से बचाए जाते हैं। प्रकाशितवाक्य में, परमेश्वर का क्रोध और मेम्ने का क्रोध एक ही बात है।</p>",
    "associations": {
      "passage": [],
      "resource": []
    }
  }
]