[
  {
    "content_id": 183037,
    "reference_id": 108143,
    "version": "1.0.0",
    "title": "मसीह का शरीर",
    "media_type": "Text",
    "index_reference": "मसीह का शरीर",
    "language": "hin",
    "content": "<p>यीशु के अनुयायियों के समुदाय का वर्णन करने का एक तरीका। यह एक चित्र है जो बताता है कि कैसे कलीसिया में हर कोई एक-दूसरे से प्यार करता है और सेवा करता है। मसीह का शरीर कई अलग-अलग लोगों से बना है जो एक साथ लाए जाते हैं। यीशु पर विश्वास करना और उसकी आज्ञा का पालन करना ही उन्हें एक बनाता है। अपने विभिन्न वरदानों का उपयोग करते हुए, वे मिलकर पृथ्वी पर यीशु का काम जारी रखते हैं।</p>",
    "associations": {
      "passage": [],
      "resource": []
    }
  }
]