[
  {
    "content_id": 761270,
    "reference_id": 108203,
    "version": "1.0.0",
    "title": "Adam",
    "media_type": "Text",
    "index_reference": "adam",
    "language": "nld",
    "content": "<p>De eerste mens die God schiep was Adam. Eva was zijn vrouw. In het Hebreeuws betekent de naam Adam &apos;mens&apos; en lijkt het op het Hebreeuwse woord voor &apos;grond&apos;. God maakte Adam van stof en blies de levensadem in hem. Hij had een vriendschappelijke en vredige relatie met God terwijl hij in de Hof van Eden leefde. Samen met Eva zorgde hij voor de tuin. Hij gaf namen aan alle wezens die God had gemaakt. Adam was de vader van Kaïn, Abel en Seth. Toen Adam en Eva ophielden God te gehoorzamen, moesten ze de Hof van Eden verlaten.</p>",
    "associations": {
      "passage": [],
      "resource": []
    }
  }
]