[
  {
    "content_id": 778773,
    "reference_id": 108240,
    "version": "1.0.0",
    "title": "Jafet",
    "media_type": "Text",
    "index_reference": "jafet",
    "language": "nld",
    "content": "<p>De oudste zoon van Noach. Hij en zijn vrouw werden gered van de zondvloed omdat ze in de ark waren. Hij behandelde zijn vader met respect toen Noach dronken werd na de zondvloed. Noach sprak een zegen uit over het nageslacht van Jafet.</p>",
    "associations": {
      "passage": [],
      "resource": []
    }
  }
]