[
  {
    "content_id": 769755,
    "reference_id": 108087,
    "title": "lieve vrouw",
    "media_type": "Text",
    "index_reference": "lieve vrouw",
    "language": "nld",
    "content": "<p>Jezus sprak op een respectvolle manier tot vrouwen. Hij noemde sommige vrouwen die hij genas &quot;lieve vrouw&quot;. Andere keren noemde hij zijn moeder Maria &quot;lieve vrouw&quot;. Dit toonde zijn vriendelijkheid en zorg.</p>",
    "associations": {
      "passage": [],
      "resource": []
    }
  }
]