[
  {
    "content_id": 232027,
    "reference_id": 108058,
    "title": "Saduceos",
    "media_type": "Text",
    "index_reference": "saduceos",
    "language": "spa",
    "content": "<p>El grupo de líderes religiosos judíos con mayor autoridad en Jerusalén. Esto fue durante los tiempos del Nuevo Testamento. Estaban a cargo del templo y trabajaban estrechamente con los gobernantes romanos. No creían en los ángeles, ni que Dios resucitaría a las personas. No creían que Jesús fuera el Mesías que Dios había prometido enviar. La mayoría de los saduceos se oponían a Jesús y a sus enseñanzas.</p>",
    "associations": {
      "passage": [],
      "resource": []
    }
  }
]