[
  {
    "content_id": 232504,
    "reference_id": 108535,
    "version": "1.0.0",
    "title": "Prostituta",
    "media_type": "Text",
    "index_reference": "prostituta",
    "language": "spa",
    "content": "<p>Una persona que tiene relaciones sexuales con otros a cambio de algún tipo de pago. Algunas personas son prostitutas porque no tienen otra opción. Esto sucede con esclavos o personas que viven bajo el control de alguien. Algunas personas eligen ser prostitutas. Es su forma de ganar dinero. Los escritores en la Biblia hablan de personas que eligen ser prostitutas. Son un símbolo para personas o grupos que intentan hacer que otros pequen. También son un símbolo de no ser fieles al adorar solo a Dios. El matrimonio es la forma en que la Biblia describe la relación de Dios con su pueblo. Cuando su pueblo sirve a otros dioses, es como ser infieles en el matrimonio. Es como ser una prostituta con falsos dioses. Dios no quiere que ningún ser humano sea una prostituta con su cuerpo. Tampoco quiere que adoren a nada ni a nadie más que a él.</p>",
    "associations": {
      "passage": [],
      "resource": []
    }
  }
]