[
  {
    "content_id": 232302,
    "reference_id": 108333,
    "version": "1.0.0",
    "title": "Sacerdote",
    "media_type": "Text",
    "index_reference": "sacerdote",
    "language": "spa",
    "content": "<p>Alguien cuyo trabajo es ayudar a las personas a adorar. En el pacto del Monte Sinaí, Dios dio instrucciones sobre los sacerdotes. Ellos debían ayudar a las personas a adorarlo y enseñarles las leyes de Dios. Eran hombres de la línea familiar de Aarón y servían solo al verdadero Dios (<span data-bnType=\"resourceReference\" data-resourceId=\"108343\" data-resourceType=\"BiblicaStudyNotesKeyTerms\">Levitas</span>, <span data-bnType=\"resourceReference\" data-resourceId=\"108306\" data-resourceType=\"BiblicaStudyNotesKeyTerms\">Aarón</span>). Lo servían en la tienda sagrada y más tarde en el templo. Hacían sacrificios para el pueblo a Dios. Seguían leyes especiales para estar limpios y puros. Esto les permitía tocar cosas sagradas. También les permitía estar cerca de Dios en la tienda sagrada o en el templo. Las personas que no eran sacerdotes no podían hacer estas cosas. Dios también dijo que todos los israelitas eran sacerdotes. Esto no significaba que todos lo servían en la tienda sagrada o el templo. Significaba que cada israelita podía conocer cercanamente a Dios. Cada israelita podía servirlo y adorarlo.</p>",
    "associations": {
      "passage": [],
      "resource": [
        {
          "reference_id": 108306,
          "content_id": 232275,
          "resource_code": "BiblicaStudyNotesKeyTerms",
          "label": "Aaron",
          "language": "spa"
        },
        {
          "reference_id": 108343,
          "content_id": 232312,
          "resource_code": "BiblicaStudyNotesKeyTerms",
          "label": "Levitas",
          "language": "spa"
        }
      ]
    }
  }
]