[
  {
    "content_id": 232318,
    "reference_id": 108349,
    "version": "1.0.0",
    "title": "Vestiduras sacerdotales",
    "media_type": "Text",
    "index_reference": "vestiduras sacerdotales",
    "language": "spa",
    "content": "<p>Ropa especial que los sacerdotes usaban cuando trabajaban en la tienda sagrada o el templo. La vestidura incluía un cinturón, túnicas exteriores, túnicas interiores y ropa interior. Incluían un turbante con una placa de oro. La vestidura para el sumo sacerdote incluía un delantal y un pectoral de lino. El pectoral sostenía el Urim y el Tumim. Estas eran piedras especiales que ayudaban al sacerdote a saber lo que Dios quería que se hiciera. Las vestiduras sacerdotales ayudaban a separar a los sacerdotes para su trabajo, para Dios.</p>",
    "associations": {
      "passage": [],
      "resource": []
    }
  }
]