[
  {
    "content_id": 232171,
    "reference_id": 108202,
    "title": "Seres humanos",
    "media_type": "Text",
    "index_reference": "seres humanos",
    "language": "spa",
    "content": "<p>Dios creó a los seres humanos a su semejanza. Quería que vivieran para siempre en completa paz con él. Debían vivir en paz unos con otros y con el resto de la creación. Pero Adán y Eva pecaron. Desde entonces, el pecado y la muerte han tenido control sobre los seres humanos, los cuales pecan y también mueren.</p>",
    "associations": {
      "passage": [],
      "resource": []
    }
  }
]