[
  {
    "content_id": 367527,
    "reference_id": 108036,
    "version": "1.0.0",
    "title": "Galilaya",
    "media_type": "Text",
    "index_reference": "galilaya",
    "language": "swh",
    "content": "<p>Eneo la kaskazini mwa ardhi ambayo Mungu alikuwa ameahidi kumpa ukoo wa Abrahamu. Ilijumuisha sehemu ya ufalme wa kaskazini wa Israeli. Ilitawaliwa na Herode Antipa katika wakati wa Yesu. Yesu alikulia Galilaya. Bahari ya Galilaya ilikuwa ziwa maarufu katika eneo hilo. Mto Yordani unatiririka kuelekea kusini kutoka humo. Hadithi nyingi kutoka maisha ya Yesu zilitokea Galilaya na karibu na Bahari ya Galilaya.</p>",
    "associations": {
      "passage": [],
      "resource": []
    }
  }
]