[
  {
    "content_id": 367990,
    "reference_id": 108499,
    "version": "1.0.0",
    "title": "Mahali pa juu",
    "media_type": "Text",
    "index_reference": "mahali pa juu",
    "language": "swh",
    "content": "<p>Mahali pa ibada kwenye kilima, mlima au sehemu ya juu. Watu walichoma uvumba na kutoa dhabihu hapo. Baadhi ya mahali pa juu yalitumika kwa kumwabudu Mungu wa kweli. Hii ilitokea mara nyingi kabla ya hekalu kujengwa. Mahali pengine pa juu yalitumika kwa kuabudu miungu ya uongo. Watu walitoa hata watoto dhabihu ili kuheshimu miungu ya uongo. Kulikuwa na mahali pengi pa juu wakati Waisraeli walipoingia Kanaani kwa mara ya kwanza. Waisraeli walipaswa kuharibu mahali pote pa juu yaliyotumika kuabudu miungu ya uongo.</p>",
    "associations": {
      "passage": [],
      "resource": []
    }
  }
]