[
  {
    "content_id": 367688,
    "reference_id": 108197,
    "title": "Uumbaji",
    "media_type": "Text",
    "index_reference": "uumbaji",
    "language": "swh",
    "content": "<p>Kila kitu kilichopo kiliumbwa na Mungu. Hii inajumuisha ardhi, bahari, anga na kila kitu kilichomo ndani yake. Pia inajumuisha kila kitu katika ulimwengu wa mbinguni. Yote ambayo Mungu aliumba yalikuwa mazuri alipoyaumba. Uumbaji unateseka kwa sababu ya dhambi za wanadamu. Mungu ataikomboa kutoka kwa athari za dhambi katika uumbaji mpya. (<span data-bnType=\"resourceReference\" data-resourceId=\"108543\" data-resourceType=\"BiblicaStudyNotesKeyTerms\">Uumbaji mpya</span>).</p>",
    "associations": {
      "passage": [],
      "resource": [
        {
          "reference_id": 108543,
          "content_id": 368034,
          "resource_code": "BiblicaStudyNotesKeyTerms",
          "label": "Uumbaji mpya",
          "language": "swh"
        }
      ]
    }
  }
]