[
  {
    "content_id": 367982,
    "reference_id": 108491,
    "title": "Yoashi",
    "media_type": "Text",
    "index_reference": "yoashi",
    "language": "swh",
    "content": "<p>Mwana wa Ahazia na Zibia. Alikuwa baba wa Amazia na alikuwa kutoka kabila la Yuda. Alikuwa mfalme wa saba wa ufalme wa kusini. Bibi yake Athalia alijaribu kumuua lakini shangazi yake Yehosheba alimwokoa. Yoashi alikulia hekaluni na Yehoyada. Alikuwa mfalme alipokuwa na umri wa miaka saba. Alihakikisha kwamba hekalu lilirekebishwa. Alimfuata Mungu kwa uaminifu na kuwaongoza watu kumwabudu Mungu pekee. Alifanya hivi kwa muda wote ambao Yehoyada alikuwa hai. Baada ya Yehoyada kufa, Yoashi alifanya mambo mabaya na kuabudu miungu ya uongo.</p>",
    "associations": {
      "passage": [],
      "resource": []
    }
  }
]