[
  {
    "content_id": 203595,
    "reference_id": 108460,
    "version": "1.0.0",
    "title": "Abigail",
    "media_type": "Text",
    "index_reference": "abigail",
    "language": "ind",
    "content": "<p>Seorang perempuan yang bijaksana menikah dengan seorang laki-laki yang bodoh bernama Nabal. Dia meyakinkan Daud untuk percaya kepada Allah dibandingkan membunuh orang dikarenakan kemarahannya. Setelah Nabal meninggal, Abigail menjadi salah satu istri dari Daud. Ia memiliki seorang anak laki-laki dengan Daud.</p>",
    "associations": {
      "passage": [],
      "resource": []
    }
  }
]