[
  {
    "content_id": 203585,
    "reference_id": 108450,
    "title": "Hana",
    "media_type": "Text",
    "index_reference": "hana",
    "language": "ind",
    "content": "<p>Ibu dari nabi Samuel. Elkana adalah suaminya. Untuk waktu yang lama ia tidak dapat memiliki anak. Kemudian Allah mengizinkannya untuk mengandung. Dengan penuh rasa syukur, ia berdoa dengan doa yang indah mengenai pemeliharaan Allah atas umat-Nya.</p>",
    "associations": {
      "passage": [],
      "resource": []
    }
  }
]