[
  {
    "content_id": 203648,
    "reference_id": 108513,
    "title": "Ezra",
    "media_type": "Text",
    "index_reference": "ezra",
    "language": "ind",
    "content": "<p>Seorang imam yang memimpin kelompok orang Yahudi untuk kembali dari Babel ke Yerusalem. Ia juga merupakan seorang ahli Taurat. Ia adalah anak dari Seraya. Ia berasal dari garis keturunan Harun dalam suku Lewi. Ezra mengajarkan kepada orang Yahudi di Yerusalem tentang Hukum Musa. Hal ini terjadi setelah mereka tinggal di Babel selama beberapa tahun. </p>",
    "associations": {
      "passage": [],
      "resource": []
    }
  }
]