[
  {
    "content_id": 203539,
    "reference_id": 108404,
    "title": "Membuang undi",
    "media_type": "Text",
    "index_reference": "membuang undi",
    "language": "ind",
    "content": "<p>Sebuah proses untuk membantu orang-orang memutuskan sesuatu. Prose ini sangat umum diantara kelompok-kelompok orang yang tinggal di sekitar bangsa Israel. Allah mengizinkan umat-Nya menggunakan praktik ini. Tidak diketahui secara pasti apa yang dilakukan orang-orang ketika mereka membuang undi. Bangsa Israel percaya bahwa Allah akan membimbing mereka untuk membuat keputusan yang bijaksana melalui pembuangan undi.</p>",
    "associations": {
      "passage": [],
      "resource": []
    }
  }
]