[
  {
    "content_id": 203525,
    "reference_id": 108390,
    "version": "1.0.0",
    "title": "Kaleb",
    "media_type": "Text",
    "index_reference": "kaleb",
    "language": "ind",
    "content": "<p>Seorang laki-laki yang terlahir sebagai budak di Mesir yang memasuki tanah Kanaan bersama-sama dengan bangsa Israel. Ia tidak berasal dari garis keturunan Yakub. Ia merupakan pengintai dari suku Yehuda yang menjelajahi tanah Kanaan. Ia membawa kabar yang baik. Kaleb taat sepenuhnya kepada Allah.</p>",
    "associations": {
      "passage": [],
      "resource": []
    }
  }
]