[
  {
    "content_id": 203343,
    "reference_id": 108208,
    "title": "Pekerjaan",
    "media_type": "Text",
    "index_reference": "pekerjaan",
    "language": "ind",
    "content": "<p>Setelah Allah menciptakan manusia pertama, Ia memberi mereka pekerjaan yang harus mereka lakukan. Pekerjaan manusia adalah menjadi penguasa bagi dunia yang dimiliki Allah (penguasa). Pekerjaan ini adalah berkat bagi manusia. Pekerjaan ini mencakup bercocok tanam. Pekerjaan ini mencakup berbagai cara manusia memelihara apa yang telah Allah berikan kepada mereka. Allah ingin manusia mengikuti teladan-Nya dalam hal bekerja dan beristirahat. Allah tidak ingin manusia bermalas-malasan. Manusia harus melakukan yang terbaik untuk menafkahi diri mereka sendiri, keluarga mereka dan komunitas mereka.</p>",
    "associations": {
      "passage": [],
      "resource": [
        {
          "reference_id": 108209,
          "content_id": 203344,
          "resource_code": "Unknown",
          "label": "Penguasa- penguasa",
          "language": "ind"
        }
      ]
    }
  }
]