[
  {
    "content_id": 203398,
    "reference_id": 108263,
    "version": "1.0.0",
    "title": "Ujian",
    "media_type": "Text",
    "index_reference": "ujian",
    "language": "ind",
    "content": "<p>Saat-saat ketika orang harus membuat pilihan yang sulit. Mereka harus memilih antara menaati Allah atau melakukan apa yang ingin mereka lakukan. Pilihan yang mereka ambil menunjukkan apakah mereka mempercayai Allah untuk menyediakan apa yang mereka butuhkan. Tujuan di balik ujian bukanlah untuk membuat orang melakukan kesalahan atau membuat mereka menderita. Tujuannya adalah agar mereka menerima lebih banyak kasih karunia Allah. Allah menguji manusia untuk membantu iman mereka kepada-Nya bertumbuh lebih kuat.</p>",
    "associations": {
      "passage": [],
      "resource": []
    }
  }
]